simple_smtp_mailer/__init__.py
simple_smtp_mailer/basic.py
simple_smtp_mailer/mail.py
simple_smtp_mailer-0.1.dist-info/LICENSE
simple_smtp_mailer-0.1.dist-info/METADATA
simple_smtp_mailer-0.1.dist-info/WHEEL
simple_smtp_mailer-0.1.dist-info/top_level.txt
simple_smtp_mailer-0.1.dist-info/RECORD
